pyresponse/__init__.py
pyresponse/config.py
pyresponse/logging.py
pyresponse/response.py
pyresponse-0.0.1.dist-info/LICENSE
pyresponse-0.0.1.dist-info/METADATA
pyresponse-0.0.1.dist-info/WHEEL
pyresponse-0.0.1.dist-info/top_level.txt
pyresponse-0.0.1.dist-info/RECORD
