Metadata-Version: 2.1
Name: pyresponse
Version: 0.0.1
Summary: Package for creating success and error responses in Python Projects
Author: Ibrahim Oluwapeluwa
Author-email: ipeluwa@gmail.com
Classifier: Development Status :: 4 - Beta
Classifier: License :: OSI Approved :: MIT License
Classifier: Programming Language :: Python :: 3
Classifier: Programming Language :: Python :: 3.6
Classifier: Programming Language :: Python :: 3.7
Classifier: Programming Language :: Python :: 3.8
Classifier: Programming Language :: Python :: 3.9
License-File: LICENSE
Requires-Dist: rollbar
Requires-Dist: sentry-sdk
Requires-Dist: python-dotenv
Requires-Dist: pydantic
Requires-Dist: marshmallow
